setup.py
caroso1222_distributions.egg-info/PKG-INFO
caroso1222_distributions.egg-info/SOURCES.txt
caroso1222_distributions.egg-info/dependency_links.txt
caroso1222_distributions.egg-info/not-zip-safe
caroso1222_distributions.egg-info/top_level.txt
distributions/Binomialdistribution.py
distributions/Gaussiandistribution.py
distributions/Generaldistribution.py
distributions/__init__.py